mover/__init__.py
mover/pipeline.py
mover/stats.py
mover/converter/__init__.py
mover/converter/mover_converter.py
mover/converter/assets/EasePack.min.js
mover/converter/assets/MotionPathPlugin.min.js
mover/converter/assets/api.js
mover/converter/assets/convert.js
mover/converter/assets/grid.svg
mover/converter/assets/gsap.min.js
mover/converter/assets/index.css
mover/converter/assets/vis.js
mover/dsl/__init__.py
mover/dsl/fol_domain.py
mover/dsl/fol_executor.py
mover/dsl/fol_parser.py
mover/dsl/mover_verifier.py
mover/dsl/utils.py
mover/dsl/assets/correction_msg_template.md
mover/nlg/__init__.py
mover/nlg/data_classes.py
mover/nlg/mover_fol_generator.py
mover/nlg/prompt_generator.py
mover/nlg/utils.py
mover/nlg/assets/sentence_patterns.json
mover/nlg/assets/vocab.json
mover/nlg/sentence_generation/__init__.py
mover/nlg/sentence_generation/sentence_composer.py
mover/nlg/sentence_generation/sentence_unit.py
mover/nlg/sentence_generation/vocab.py
mover/synthesizers/__init__.py
mover/synthesizers/animation_synthesizer.py
mover/synthesizers/base_synthesizer.py
mover/synthesizers/llm_client.py
mover/synthesizers/mover_synthesizer.py
mover/synthesizers/prompt_rewriter.py
mover/synthesizers/utils.py
mover/synthesizers/assets/sys_msg_animation_synthesizer.md
mover/synthesizers/assets/sys_msg_mover_synthesizer.md
mover/synthesizers/assets/sys_msg_prompt_rewriter.md
mover/synthesizers/assets/sys_msg_test.md
mover/synthesizers/assets/template.html
mover-0.1.5.dist-info/licenses/LICENSE
mover-0.1.5.dist-info/METADATA
mover-0.1.5.dist-info/WHEEL
mover-0.1.5.dist-info/top_level.txt
mover-0.1.5.dist-info/RECORD
