Metadata-Version: 2.4
Name: mover
Version: 0.1.5
Summary: Official implementation of MoVer: Motion Verification for Motion Graphics Animations
Author-email: Jiaju Ma <jiajuma@stanford.edu>
License: Apache-2.0
Project-URL: Homepage, https://mover-dsl.github.io/
Project-URL: Repository, https://github.com/jama1017/MoVer
Project-URL: Bug Tracker, https://github.com/jama1017/MoVer/issues
Classifier: Development Status :: 4 - Beta
Classifier: Programming Language :: Python :: 3
Classifier: Programming Language :: Python :: 3.10
Classifier: Programming Language :: Python :: 3.11
Classifier: Programming Language :: Python :: 3.12
Classifier: Topic :: Scientific/Engineering :: Artificial Intelligence
Classifier: Topic :: Multimedia :: Graphics
Requires-Python: >=3.10
License-File: LICENSE
Requires-Dist: cairosvg
Requires-Dist: fastapi==0.115.14
Requires-Dist: groq
Requires-Dist: Jinja2
Requires-Dist: numpy
Requires-Dist: openai
Requires-Dist: opencv-contrib-python==4.11.0.86
Requires-Dist: Pillow
Requires-Dist: playwright
Requires-Dist: protobuf
Requires-Dist: PyYAML
Requires-Dist: treelib
Requires-Dist: uvicorn==0.35.0
Requires-Dist: torch
Requires-Dist: torchvision
Requires-Dist: ipykernel>=6.29.5
Requires-Dist: pyrealb
Provides-Extra: local
Requires-Dist: ollama-python; extra == "local"
Requires-Dist: vllm; extra == "local"
Dynamic: license-file
